httpackage/__init__.py
httpackage/httpackage.py
httpackage-1.0.1.dist-info/LICENSE
httpackage-1.0.1.dist-info/METADATA
httpackage-1.0.1.dist-info/WHEEL
httpackage-1.0.1.dist-info/top_level.txt
httpackage-1.0.1.dist-info/RECORD
