Metadata-Version: 2.1
Name: httpackage
Version: 1.0.1
Summary: Fixed description, old version yanked.
Author: PyModuleDev
Author-email: pxcom@mail.com
Classifier: Development Status :: 5 - Production/Stable
Classifier: Intended Audience :: Developers
Classifier: License :: OSI Approved :: Apache Software License
Classifier: Programming Language :: Python :: 3
Requires-Python: >=3.6
License-File: LICENSE
